{"width":1024,"imagePath":"zombie03_tex.png","height":512,"name":"zombie03","SubTexture":[{"width":85,"y":116,"height":28,"name":"椭圆_1","x":506},{"width":27,"y":448,"height":14,"name":"右腿3","x":1},{"width":18,"y":134,"height":12,"name":"右腿2","x":593},{"width":32,"y":98,"height":15,"name":"左腿3","x":577},{"width":20,"y":115,"height":17,"name":"左腿2","x":593},{"width":23,"y":479,"height":26,"name":"左腿1","x":1},{"width":25,"y":454,"height":28,"name":"右腿1","x":449},{"width":44,"y":434,"height":18,"name":"跨","x":449},{"width":69,"y":47,"height":67,"name":"身体","x":506},{"width":30,"y":434,"height":44,"name":"左手1","x":417},{"width":32,"y":47,"height":49,"name":"左手2","x":577},{"width":31,"y":434,"height":43,"name":"右手1","x":384},{"width":36,"y":433,"height":52,"name":"右手2","x":499},{"width":49,"y":1,"height":55,"name":"头","x":723},{"frameY":-5,"y":150,"frameWidth":150,"frameX":-14,"frameHeight":150,"width":119,"height":140,"name":"合成 3_00020","x":384},{"frameY":-4,"y":1,"frameWidth":150,"frameX":-12,"frameHeight":150,"width":126,"height":147,"name":"合成 3_00004","x":1},{"frameY":-4,"y":1,"frameWidth":150,"frameX":-13,"frameHeight":150,"width":125,"height":147,"name":"合成 3_00014","x":257},{"frameY":-4,"y":1,"frameWidth":150,"frameX":-12,"frameHeight":150,"width":126,"height":147,"name":"合成 3_00002","x":129},{"frameY":-4,"y":150,"frameWidth":150,"frameX":-12,"frameHeight":150,"width":126,"height":147,"name":"合成 3_00010","x":129},{"frameY":-4,"y":150,"frameWidth":150,"frameX":-13,"frameHeight":150,"width":125,"height":147,"name":"合成 3_00016","x":257},{"frameY":-4,"y":299,"frameWidth":150,"frameX":-12,"frameHeight":150,"width":126,"height":147,"name":"合成 3_00008","x":1},{"frameY":-10,"y":1,"frameWidth":150,"frameX":-16,"frameHeight":150,"width":108,"height":107,"name":"合成 3_00028","x":613},{"frameY":-4,"y":150,"frameWidth":150,"frameX":-12,"frameHeight":150,"width":126,"height":147,"name":"合成 3_00006","x":1},{"frameY":-4,"y":299,"frameWidth":150,"frameX":-12,"frameHeight":150,"width":126,"height":147,"name":"合成 3_00000","x":129},{"frameY":-6,"y":292,"frameWidth":150,"frameX":-15,"frameHeight":150,"width":112,"height":139,"name":"合成 3_00024","x":499},{"frameY":-5,"y":292,"frameWidth":150,"frameX":-15,"frameHeight":150,"width":113,"height":140,"name":"合成 3_00022","x":384},{"frameY":-8,"y":150,"frameWidth":150,"frameX":-16,"frameHeight":150,"width":110,"height":137,"name":"合成 3_00026","x":505},{"frameY":-4,"y":1,"frameWidth":150,"frameX":-14,"frameHeight":150,"width":120,"height":147,"name":"合成 3_00018","x":384},{"frameY":-11,"y":110,"frameWidth":150,"frameX":-17,"frameHeight":150,"width":107,"height":105,"name":"合成 3_00029","x":617},{"frameY":-4,"y":299,"frameWidth":150,"frameX":-13,"frameHeight":150,"width":125,"height":147,"name":"合成 3_00012","x":257},{"frameY":-65,"y":1,"frameWidth":150,"frameX":-18,"frameHeight":150,"width":105,"height":44,"name":"合成 3_00030","x":506}]}