{"width":2048,"imagePath":"board_maxi_tex_1.png","height":4096,"name":"board_maxi","SubTexture":[{"frameY":-16,"y":979,"frameWidth":800,"frameX":-81,"frameHeight":500,"width":644,"height":473,"name":"maxi结束_00009","x":1269},{"frameY":-16,"y":504,"frameWidth":800,"frameX":-81,"frameHeight":500,"width":645,"height":473,"name":"maxi维持_00009","x":1272},{"frameY":0,"y":2,"frameWidth":800,"frameX":-91,"frameHeight":500,"width":618,"height":500,"name":"maxi出现_00021","x":2},{"frameY":-16,"y":979,"frameWidth":800,"frameX":-81,"frameHeight":500,"width":645,"height":473,"name":"maxi维持_00021","x":622},{"frameY":-16,"y":2406,"frameWidth":800,"frameX":-91,"frameHeight":500,"width":618,"height":473,"name":"maxi维持_00020","x":1242},{"frameY":-44,"y":1454,"frameWidth":800,"frameX":-2,"frameHeight":500,"width":735,"height":412,"name":"maxi出现_00008","x":2},{"frameY":0,"y":2,"frameWidth":800,"frameX":-91,"frameHeight":500,"width":618,"height":500,"name":"maxi出现_00020","x":622},{"frameY":-16,"y":3356,"frameWidth":800,"frameX":-91,"frameHeight":500,"width":618,"height":473,"name":"maxi维持_00007","x":1242},{"frameY":-16,"y":2882,"frameWidth":800,"frameX":-91,"frameHeight":500,"width":618,"height":473,"name":"maxi维持_00019","x":622},{"frameY":-16,"y":2820,"frameWidth":800,"frameX":-91,"frameHeight":500,"width":618,"height":474,"name":"maxi结束_00004","x":2},{"frameY":-16,"y":3296,"frameWidth":800,"frameX":-91,"frameHeight":500,"width":618,"height":473,"name":"maxi维持_00017","x":2},{"frameY":-16,"y":2881,"frameWidth":800,"frameX":-91,"frameHeight":500,"width":618,"height":473,"name":"maxi维持_00004","x":1242},{"frameY":-50,"y":1006,"frameWidth":800,"frameX":-88,"frameHeight":500,"width":578,"height":400,"name":"maxi出现_00006","x":2},{"frameY":-16,"y":2344,"frameWidth":800,"frameX":-91,"frameHeight":500,"width":618,"height":474,"name":"maxi结束_00003","x":2},{"frameY":-16,"y":3357,"frameWidth":800,"frameX":-91,"frameHeight":500,"width":618,"height":473,"name":"maxi维持_00015","x":622},{"frameY":-16,"y":1868,"frameWidth":800,"frameX":-91,"frameHeight":500,"width":618,"height":474,"name":"maxi维持_00002","x":2},{"frameY":-16,"y":1930,"frameWidth":800,"frameX":-91,"frameHeight":500,"width":618,"height":474,"name":"maxi结束_00002","x":1242},{"frameY":-16,"y":2406,"frameWidth":800,"frameX":-91,"frameHeight":500,"width":618,"height":474,"name":"maxi结束_00001","x":622},{"frameY":-16,"y":1454,"frameWidth":801,"frameX":-91,"frameHeight":500,"width":619,"height":474,"name":"maxi结束_00000","x":739},{"frameY":-16,"y":1454,"frameWidth":800,"frameX":-91,"frameHeight":500,"width":618,"height":474,"name":"maxi维持_00001","x":1360},{"frameY":-16,"y":1930,"frameWidth":800,"frameX":-91,"frameHeight":500,"width":618,"height":474,"name":"maxi维持_00000","x":622},{"frameY":0,"y":2,"frameWidth":800,"frameX":-91,"frameHeight":500,"width":618,"height":500,"name":"maxi出现_00023","x":1242},{"frameY":0,"y":504,"frameWidth":800,"frameX":-91,"frameHeight":500,"width":618,"height":500,"name":"maxi出现_00022","x":2},{"frameY":-16,"y":504,"frameWidth":800,"frameX":-76,"frameHeight":500,"width":648,"height":473,"name":"maxi结束_00010","x":622}]}